3.2.3(Verificación)/ALU_Custom.v
//-------------------------------------------------------------------------
// ALU_Custom.v
//-------------------------------------------------------------------------
// This file is generated by PyMTL SystemVerilog translation pass.

// PyMTL Component ALU Definition
// Full name: ALU_noparam
// At c:\Users\egroj\Downloads\TFGCODIGO\Capacidades-3.1_&_3.2\ALU.py

module ALU_Custom
(
  input  logic [0:0] clk ,
  input  logic [1:0] fn ,
  input  logic [7:0] in0 ,
  input  logic [7:0] in1 ,
  output logic [7:0] out ,
  input  logic [0:0] reset 
);

  // PyMTL Update Block Source
  // At c:\Users\egroj\Downloads\TFGCODIGO\Capacidades-3.1_&_3.2\ALU.py:12
  // @update
  // def up_alu():
  //     if s.fn == 0:
  //         s.out @= s.in0 + s.in1
  //     elif s.fn == 1:
  //         s.out @= s.in0 - s.in1
  //     elif s.fn == 2:
  //         s.out @= s.in0 & s.in1
  //     elif s.fn == 3:
  //         s.out @= ~s.in0 + 1
  //     else:
  //         s.out @= 0
  
  always_comb begin : up_alu
    if ( fn == 2'd0 ) begin
      out = in0 + in1;
    end
    else if ( fn == 2'd1 ) begin
      out = in0 - in1;
    end
    else if ( fn == 2'd2 ) begin
      out = in0 & in1;
    end
    else if ( fn == 2'd3 ) begin
      out = ( ~in0 ) + 8'd1;
    end
    else
      out = 8'd0;
  end

endmodule

3.2.3(Verificación)/dump.vcd
$version Generated by VerilatedVcd $end
$timescale 1ps $end
 $scope module TOP $end
  $var wire 1 # clk [0:0] $end
  $var wire 2 $ fn [1:0] $end
  $var wire 8 % in0 [7:0] $end
  $var wire 8 & in1 [7:0] $end
  $var wire 8 ' out [7:0] $end
  $var wire 1 ( reset [0:0] $end
  $scope module ALU_Custom $end
   $var wire 1 # clk [0:0] $end
   $var wire 2 $ fn [1:0] $end
   $var wire 8 % in0 [7:0] $end
   $var wire 8 & in1 [7:0] $end
   $var wire 8 ' out [7:0] $end
   $var wire 1 ( reset [0:0] $end
  $upscope $end
 $upscope $end
$enddefinitions $end


#0
0#
b00 $
b00000011 %
b00000010 &
b00000101 '
0(
#1
b01 $
b00000101 %
b00000011 &
b00000010 '
#2
b10 $
b00000110 %
#3
b11 $
b00000100 %
b00000000 &
b11111100 '
#4
b00 $          // Suma
b00000001 %    // in0 = 1
b00000001 &    // in1 = 1
b00000010 '    // out = 2
#5
b01 $          // Resta
b00000010 %    // in0 = 2
b00000001 &    // in1 = 1
b00000001 '    // out = 1
#6
b10 $          // Operación lógica (ejemplo: AND)
b00000011 %    // in0 = 3
b00000010 &    // in1 = 2
b00000010 '    // out = 2 (resultado de AND)
#7
b11 $          // Operación lógica (ejemplo: OR)
b00000011 %    // in0 = 3
b00000001 &    // in1 = 1
b11111110 '    // out = 254 (resultado de OR)
#8
b00 $          // Suma
b00000110 %    // in0 = 6
b00000011 &    // in1 = 3
b00000101 '    // out = 9
#9
b01 $          // Resta
b00000111 %    // in0 = 7
b00000010 &    // in1 = 2
b00000101 '    // out = 5
#10
b10 $          // Operación lógica (ejemplo: AND)
b00000101 %    // in0 = 5
b00000001 &    // in1 = 1
b00000001 '    // out = 1 (resultado de AND)
#11
b11 $          // Operación lógica (ejemplo: OR)
b00000000 %    // in0 = 0
b00000000 &    // in1 = 0
b00000000 '    // out = 0 (resultado de OR)
#12
b00 $          // Suma
b00000010 %    // in0 = 2
b00000100 &    // in1 = 4
b00000110 '    // out = 6
#13
b01 $          // Resta
b00001000 %    // in0 = 8
b00000111 &    // in1 = 7
b00000001 '    // out = 1
#14
b10 $          // Operación lógica (ejemplo: AND)
b00001100 %    // in0 = 12
b00000011 &    // in1 = 3
b00000000 '    // out = 0 (resultado de AND)
#15
b11 $          // Operación lógica (ejemplo: OR)
b00000010 %    // in0 = 2
b00000101 &    // in1 = 5
b00000111 '    // out = 7 (resultado de OR)